LICENSE
MANIFEST.in
README.md
VERSION
requirements.txt
setup.cfg
setup.py
powerful_pipes_watch_bus/__init__.py
powerful_pipes_watch_bus/__main__send_message__.py
powerful_pipes_watch_bus/__main__watch_bus__.py
powerful_pipes_watch_bus/config.py
powerful_pipes_watch_bus/exceptions.py
powerful_pipes_watch_bus.egg-info/PKG-INFO
powerful_pipes_watch_bus.egg-info/SOURCES.txt
powerful_pipes_watch_bus.egg-info/dependency_links.txt
powerful_pipes_watch_bus.egg-info/entry_points.txt
powerful_pipes_watch_bus.egg-info/requires.txt
powerful_pipes_watch_bus.egg-info/top_level.txt
powerful_pipes_watch_bus.egg-info/zip-safe
powerful_pipes_watch_bus/brokers/__init__.py
powerful_pipes_watch_bus/brokers/connect.py
powerful_pipes_watch_bus/brokers/interface.py
powerful_pipes_watch_bus/brokers/redis.py
powerful_pipes_watch_bus/examples/__init__.py
powerful_pipes_watch_bus/examples/send_message.py