Metadata-Version: 2.1
Name: powerful-pipes-watch-bus
Version: 1.0.3
Summary: Multi broker watcher tool that connect them with UNIX pipes. BUS Message watcher for OpenAPI Generator Project
Home-page: https://github.com/42Crunch/powerful-pipes-bus-watcher
Author: 42Crunch team
Author-email: dev@42crunch.com
License: License :: OSI Approved :: GNU Affero General Public License v3 or later (AGPLv3+)
Platform: UNKNOWN
Classifier: License :: OSI Approved :: GNU Affero General Public License v3 or later (AGPLv3+)
Classifier: Programming Language :: Python :: 3.8
Classifier: Programming Language :: Python :: 3.9
Classifier: Environment :: Console
Classifier: Operating System :: POSIX
Classifier: Operating System :: MacOS
Classifier: Operating System :: OS Independent
Classifier: Operating System :: Microsoft :: Windows
Classifier: Intended Audience :: Other Audience
Classifier: Intended Audience :: System Administrators
